aiosofascore/__init__.py
aiosofascore/client.py
aiosofascore/exception.py
aiosofascore/adapters/__init__.py
aiosofascore/adapters/http_client.py
aiosofascore/api/__init__.py
aiosofascore/api/soccer/__init__.py
aiosofascore/api/soccer/services/__init__.py
aiosofascore/api/soccer/services/search/__init__.py
aiosofascore/api/soccer/services/search/models.py
aiosofascore/api/soccer/services/search/repo.py
aiosofascore/api/soccer/services/search/service.py
aiosofascore/api/soccer/services/team/__init__.py
aiosofascore/api/soccer/services/team/base.py
aiosofascore/api/soccer/services/team/common.py
aiosofascore/api/soccer/services/team/models.py
aiosofascore/api/soccer/services/team/repo.py
aiosofascore/api/soccer/services/team/service.py
aiosofascore-0.1.1.0.dist-info/licenses/LICENSE
aiosofascore-0.1.1.0.dist-info/METADATA
aiosofascore-0.1.1.0.dist-info/WHEEL
aiosofascore-0.1.1.0.dist-info/top_level.txt
aiosofascore-0.1.1.0.dist-info/RECORD
