Metadata-Version: 2.4
Name: aiosofascore
Version: 0.1.1.0
Summary: API client for SofaScore soccer data
Home-page: https://github.com/Rooney27/aio_sofascore
Author: Philip
Author-email: vasilewskij.fil@gmail.com
Classifier: Programming Language :: Python :: 3
Classifier: License :: OSI Approved :: MIT License
Classifier: Operating System :: OS Independent
Requires-Python: >=3.10
License-File: LICENSE
Requires-Dist: aiohttp
Requires-Dist: pydantic
Dynamic: author
Dynamic: author-email
Dynamic: classifier
Dynamic: description
Dynamic: description-content-type
Dynamic: home-page
Dynamic: license-file
Dynamic: requires-dist
Dynamic: requires-python
Dynamic: summary
